lazybuild/__init__.py
lazybuild/aws.py
lazybuild/gmBuilder.py
lazybuild/lazybuild.py
lazybuild/ssh.py
lazybuild/resources/options/build.bff
lazybuild/resources/options/macros.json
lazybuild/resources/options/preferences.json
lazybuild/resources/options/targetoptions.json
lazybuild-1.0.3.dist-info/METADATA
lazybuild-1.0.3.dist-info/WHEEL
lazybuild-1.0.3.dist-info/entry_points.txt
lazybuild-1.0.3.dist-info/top_level.txt
lazybuild-1.0.3.dist-info/RECORD
