Metadata-Version: 2.1
Name: lazybuild
Version: 1.0.3
Summary: A remote compiling tool for GameMaker Studio 2.
Home-page: https://github.com/imlazyeye/lazybuild
Author: lazyeye
Author-email: imlazyeye@gmail.com
License: MIT
Platform: UNKNOWN
Classifier: License :: OSI Approved :: MIT License
Classifier: Programming Language :: Python :: 3
Classifier: Programming Language :: Python :: 3.7
Requires-Dist: boto3
Requires-Dist: paramiko
Requires-Dist: termcolor
Requires-Dist: colorama
